TaxSEA/TaxSEA.py
TaxSEA/__init__.py
TaxSEA/__main__.py
TaxSEA/gmt_tools.py
TaxSEA-0.0.5.dist-info/LICENSE
TaxSEA-0.0.5.dist-info/METADATA
TaxSEA-0.0.5.dist-info/WHEEL
TaxSEA-0.0.5.dist-info/entry_points.txt
TaxSEA-0.0.5.dist-info/top_level.txt
TaxSEA-0.0.5.dist-info/RECORD
